ezflow/__init__.py
ezflow/config/__init__.py
ezflow/config/config.py
ezflow/config/retrieve.py
ezflow/data/__init__.py
ezflow/data/build.py
ezflow/data/dataloader/__init__.py
ezflow/data/dataloader/dataloader_creator.py
ezflow/data/dataloader/device_dataloader.py
ezflow/data/dataset/__init__.py
ezflow/data/dataset/autoflow.py
ezflow/data/dataset/base_dataset.py
ezflow/data/dataset/driving.py
ezflow/data/dataset/flying_chairs.py
ezflow/data/dataset/flying_things3d.py
ezflow/data/dataset/hd1k.py
ezflow/data/dataset/kitti.py
ezflow/data/dataset/kubric.py
ezflow/data/dataset/monkaa.py
ezflow/data/dataset/mpi_sintel.py
ezflow/decoder/__init__.py
ezflow/decoder/build.py
ezflow/decoder/context.py
ezflow/decoder/conv_decoder.py
ezflow/decoder/dilated_flow_stack_filter.py
ezflow/decoder/pyramid.py
ezflow/decoder/separable_conv.py
ezflow/decoder/iterative/__init__.py
ezflow/decoder/iterative/recurrent_lookup.py
ezflow/decoder/noniterative/__init__.py
ezflow/decoder/noniterative/operators.py
ezflow/decoder/noniterative/soft_regression.py
ezflow/encoder/__init__.py
ezflow/encoder/build.py
ezflow/encoder/conv_encoder.py
ezflow/encoder/dcvnet.py
ezflow/encoder/ganet.py
ezflow/encoder/pspnet.py
ezflow/encoder/pyramid.py
ezflow/encoder/raft.py
ezflow/encoder/residual.py
ezflow/engine/__init__.py
ezflow/engine/eval.py
ezflow/engine/profiler.py
ezflow/engine/pruning.py
ezflow/engine/registry.py
ezflow/engine/retrieve.py
ezflow/engine/trainer.py
ezflow/functional/__init__.py
ezflow/functional/registry.py
ezflow/functional/scheduler.py
ezflow/functional/weight_annealers.py
ezflow/functional/criterion/__init__.py
ezflow/functional/criterion/multiscale.py
ezflow/functional/criterion/offset.py
ezflow/functional/criterion/sequence.py
ezflow/functional/data_augmentation/__init__.py
ezflow/functional/data_augmentation/augmentor.py
ezflow/functional/data_augmentation/operations.py
ezflow/model_zoo/__init__.py
ezflow/model_zoo/model_zoo.py
ezflow/model_zoo/configs/models/dcvnet.yaml
ezflow-0.2.5.dist-info/AUTHORS.rst
ezflow-0.2.5.dist-info/LICENSE
ezflow-0.2.5.dist-info/METADATA
ezflow-0.2.5.dist-info/WHEEL
ezflow-0.2.5.dist-info/top_level.txt
ezflow-0.2.5.dist-info/RECORD
