Metadata-Version: 2.1
Name: ezflow
Version: 0.2.5
Summary: A PyTorch library for optical flow estimation using neural networks
Home-page: https://github.com/neu-vig/ezflow
Author: EzFlow Contributors
Author-email: shahnh19@gmail.com
License: MIT
Project-URL: Source, https://github.com/neu-vig/ezflow
Keywords: optical flow,pytorch,machine learning,deep learning
Classifier: Development Status :: 2 - Pre-Alpha
Classifier: Intended Audience :: Developers
Classifier: License :: OSI Approved :: MIT License
Classifier: Natural Language :: English
Classifier: Programming Language :: Python :: 3
Classifier: Programming Language :: Python :: 3.6
Classifier: Programming Language :: Python :: 3.7
Classifier: Programming Language :: Python :: 3.8
Requires-Python: >=3.6
License-File: LICENSE
License-File: AUTHORS.rst
Requires-Dist: absl-py ==0.13.0
Requires-Dist: alabaster ==0.7.12
Requires-Dist: antlr4-python3-runtime ==4.8
Requires-Dist: appdirs ==1.4.4
Requires-Dist: argh ==0.26.2
Requires-Dist: arrow ==0.15.1
Requires-Dist: attrs
Requires-Dist: Babel ==2.9.1
Requires-Dist: backports.entry-points-selectable ==1.1.0
Requires-Dist: binaryornot ==0.4.4
Requires-Dist: black ==21.7b0
Requires-Dist: bleach ==3.3.0
Requires-Dist: brotlipy ==0.7.0
Requires-Dist: bump2version ==0.5.11
Requires-Dist: cachetools ==4.2.2
Requires-Dist: certifi ==2022.12.7
Requires-Dist: cffi ==1.14.6
Requires-Dist: cfgv ==3.3.0
Requires-Dist: chardet ==4.0.0
Requires-Dist: charset-normalizer ==2.0.1
Requires-Dist: click ==8.0.1
Requires-Dist: colorama ==0.4.4
Requires-Dist: coverage ==5.5
Requires-Dist: cryptography ==3.4.8
Requires-Dist: cycler ==0.10.0
Requires-Dist: distlib ==0.3.6
Requires-Dist: dnspython ==1.16.0
Requires-Dist: docopt ==0.6.2
Requires-Dist: docutils ==0.17.1
Requires-Dist: easydict ==1.9
Requires-Dist: entrypoints ==0.3
Requires-Dist: fett ==0.3.2
Requires-Dist: filelock ==3.12.2
Requires-Dist: flake8 ==3.9.2
Requires-Dist: fvcore ==0.1.5.post20210915
Requires-Dist: grpcio ==1.39.0
Requires-Dist: identify ==2.2.13
Requires-Dist: idna ==3.2
Requires-Dist: imagesize ==1.2.0
Requires-Dist: importlib-metadata ==6.7.0
Requires-Dist: iniconfig ==1.1.1
Requires-Dist: iopath ==0.1.9
Requires-Dist: Jinja2 ==3.0.1
Requires-Dist: jinja2-time ==0.2.0
Requires-Dist: kiwisolver
Requires-Dist: Markdown ==3.3.4
Requires-Dist: MarkupSafe ==2.0.1
Requires-Dist: matplotlib ==3.4.2
Requires-Dist: mccabe ==0.6.1
Requires-Dist: mypy-extensions ==0.4.3
Requires-Dist: networkx ==2.6.2
Requires-Dist: nodeenv ==1.6.0
Requires-Dist: numpy ==1.20.2
Requires-Dist: oauthlib ==3.2.2
Requires-Dist: olefile ==0.46
Requires-Dist: omegaconf
Requires-Dist: opencv-python ==4.5.3.56
Requires-Dist: packaging ==21.0
Requires-Dist: pathspec ==0.9.0
Requires-Dist: pathtools ==0.1.2
Requires-Dist: Pillow
Requires-Dist: pkginfo ==1.7.1
Requires-Dist: platformdirs ==3.8.0
Requires-Dist: pluggy ==0.13.1
Requires-Dist: portalocker
Requires-Dist: poyo ==0.5.0
Requires-Dist: pre-commit
Requires-Dist: protobuf ==3.18.3
Requires-Dist: py ==1.10.0
Requires-Dist: pyasn1 ==0.4.8
Requires-Dist: pyasn1-modules ==0.2.8
Requires-Dist: pycodestyle ==2.7.0
Requires-Dist: pycparser ==2.20
Requires-Dist: pyflakes ==2.3.1
Requires-Dist: Pygments ==2.9.0
Requires-Dist: pymongo ==3.11.4
Requires-Dist: pyOpenSSL ==20.0.1
Requires-Dist: pyparsing ==2.4.7
Requires-Dist: PySocks ==1.7.1
Requires-Dist: pytest ==6.2.4
Requires-Dist: python-dateutil ==2.8.1
Requires-Dist: python-slugify ==5.0.2
Requires-Dist: pytz ==2021.1
Requires-Dist: PyYAML ==5.4.1
Requires-Dist: readme-renderer ==29.0
Requires-Dist: regex
Requires-Dist: requests ==2.26.0
Requires-Dist: requests-oauthlib ==1.3.0
Requires-Dist: requests-toolbelt ==0.9.1
Requires-Dist: rsa ==4.7.2
Requires-Dist: scipy ==1.7.0
Requires-Dist: six
Requires-Dist: snooty-lextudio ==1.11.1.dev0
Requires-Dist: snowballstemmer ==2.1.0
Requires-Dist: tabulate ==0.8.9
Requires-Dist: tensorboard ==2.6.0
Requires-Dist: tensorboard-data-server ==0.6.1
Requires-Dist: tensorboard-plugin-wit ==1.8.0
Requires-Dist: termcolor ==1.1.0
Requires-Dist: text-unidecode ==1.3
Requires-Dist: toml
Requires-Dist: tomli ==1.2.1
Requires-Dist: torch >=1.9.0
Requires-Dist: torchmetrics >=0.5.0
Requires-Dist: torchvision >=0.10.0
Requires-Dist: tornado
Requires-Dist: tqdm
Requires-Dist: twine ==1.14.0
Requires-Dist: typed-ast
Requires-Dist: typing-extensions ==4.6.3
Requires-Dist: Unidecode ==1.3.2
Requires-Dist: urllib3 ==1.26.6
Requires-Dist: virtualenv ==20.23.1
Requires-Dist: watchdog ==1.0.2
Requires-Dist: webencodings ==0.5.1
Requires-Dist: whichcraft ==0.6.1
Requires-Dist: yacs ==0.1.8
Requires-Dist: zipp ==3.5.0
